{
    "subject": "boxscore",
    "copyright": "Copyright 2016 MLB Advanced Media, L.P.  Use of any content on this page acknowledges agreement to the terms posted here http://gdx.mlb.com/components/copyright.txt",
    "data": {
        "boxscore": {
            "home_sname": "Chi Cubs",
            "away_fname": "St. Louis Cardinals",
            "game_info": "\n      <relief_no_out>Kiekhefer pitched to 1 batter in the 4th.</relief_no_out><br/><br/>\n      <game_score>Leake 26; Arrieta 80.</game_score><br/>\n      <wild_pitches>Leake 2.</wild_pitches><br/>\n      <pitches_to_strikes>Leake 77-44; Kiekhefer 5-3; Socolovich 21-13; Rosenthal 14-10; Tuivailala 21-9; Duke 5-3; Williams, J 24-14; Arrieta 99-68; Strop 13-6; Wood, T 7-4; Edwards Jr. 8-7.</pitches_to_strikes><br/>\n      <groundouts_to_flyouts>Leake 3-4; Kiekhefer 0-0; Socolovich 5-0; Rosenthal 1-0; Tuivailala 1-0; Duke 0-0; Williams, J 0-2; Arrieta 5-2; Strop 1-0; Wood, T 0-0; Edwards Jr. 0-1.</groundouts_to_flyouts><br/>\n      <batters_faced>Leake 20; Kiekhefer 1; Socolovich 5; Rosenthal 4; Tuivailala 4; Duke 1; Williams, J 4; Arrieta 24; Strop 3; Wood, T 1; Edwards Jr. 2.</batters_faced><br/>\n      <inherited_runners_scored>Kiekhefer 2-0; Socolovich 3-1; Duke 2-0.</inherited_runners_scored><br/>\n      <umpires>\n         <umpire id=\"427044\" position=\"HP\" name=\"CB Bucknor\"></umpire>\n         <umpire id=\"427424\" position=\"1B\" name=\"Jim Reynolds\"></umpire>\n         <umpire id=\"427090\" position=\"2B\" name=\"Fieldin Culbreth\"></umpire>\n         <umpire id=\"484499\" position=\"3B\" name=\"Manny Gonzalez\"></umpire>\n      </umpires>\n      <weather>71 degrees, overcast</weather>\n      <wind>9 mph, In from LF</wind>\n      <weather>1:22 PM</weather>\n      <time>2:53</time>\n      <attendance>40,791</attendance>\n      <wind>Wrigley Field</wind>\n      <wind>September 23, 2016</wind>",
            "home_loss": "55",
            "venue_name": "Wrigley Field",
            "linescore": {
                "home_team_runs": "5",
                "home_team_errors": "0",
                "home_team_hits": "9",
                "inning_line_score": [
                    {
                        "home": "4",
                        "away": "0",
                        "inning": "1"
                    },
                    {
                        "home": "0",
                        "away": "0",
                        "inning": "2"
                    },
                    {
                        "home": "0",
                        "away": "0",
                        "inning": "3"
                    },
                    {
                        "home": "1",
                        "away": "0",
                        "inning": "4"
                    },
                    {
                        "home": "0",
                        "away": "0",
                        "inning": "5"
                    },
                    {
                        "home": "0",
                        "away": "0",
                        "inning": "6"
                    },
                    {
                        "home": "0",
                        "away": "0",
                        "inning": "7"
                    },
                    {
                        "home": "0",
                        "away": "0",
                        "inning": "8"
                    },
                    {
                        "home": "x",
                        "away": "0",
                        "inning": "9"
                    }
                ],
                "away_team_errors": "0",
                "away_team_runs": "0",
                "away_team_hits": "5"
            },
            "home_sport_code": "mlb",
            "away_wins": "80",
            "game_pk": "449168",
            "status_ind": "F",
            "date": "September 23, 2016",
            "pitching": [
                {
                    "hr": "0",
                    "so": "4",
                    "r": "5",
                    "pitcher": [
                        {
                            "hr": "0",
                            "s_er": "90",
                            "loss": "true",
                            "np": "77",
                            "name_display_first_last": "Mike Leake",
                            "s_h": "198",
                            "era": "4.72",
                            "game_score": "26",
                            "bs": "0",
                            "pos": "P",
                            "id": "502190",
                            "name": "Leake",
                            "bf": "20",
                            "sv": "0",
                            "bb": "3",
                            "note": "(L, 9-11)",
                            "hld": "0",
                            "so": "1",
                            "s_so": "119",
                            "l": "11",
                            "h": "7",
                            "s_ip": "171.2",
                            "w": "9",
                            "s_bb": "30",
                            "s_r": "99",
                            "s": "44",
                            "r": "5",
                            "er": "5",
                            "out": "10"
                        },
                        {
                            "hr": "0",
                            "s_er": "13",
                            "np": "5",
                            "name_display_first_last": "Dean Kiekhefer",
                            "s_h": "22",
                            "era": "6.38",
                            "game_score": "38",
                            "bs": "0",
                            "pos": "P",
                            "id": "518883",
                            "name": "Kiekhefer",
                            "bf": "1",
                            "sv": "0",
                            "bb": "0",
                            "hld": "2",
                            "so": "0",
                            "s_so": "12",
                            "l": "0",
                            "h": "1",
                            "s_ip": "18.1",
                            "w": "0",
                            "s_bb": "6",
                            "s_r": "13",
                            "s": "3",
                            "r": "0",
                            "er": "0",
                            "out": "0"
                        },
                        {
                            "hr": "0",
                            "s_er": "4",
                            "np": "21",
                            "name_display_first_last": "Miguel Socolovich",
                            "s_h": "5",
                            "era": "2.25",
                            "game_score": "50",
                            "bs": "0",
                            "pos": "P",
                            "id": "462515",
                            "name": "Socolovich",
                            "bf": "5",
                            "sv": "0",
                            "bb": "0",
                            "hld": "0",
                            "so": "0",
                            "s_so": "14",
                            "l": "0",
                            "h": "0",
                            "s_ip": "16.0",
                            "w": "1",
                            "s_bb": "5",
                            "s_r": "4",
                            "s": "13",
                            "r": "0",
                            "er": "0",
                            "out": "5"
                        },
                        {
                            "hr": "0",
                            "s_er": "20",
                            "np": "14",
                            "name_display_first_last": "Trevor Rosenthal",
                            "s_h": "44",
                            "era": "4.95",
                            "game_score": "45",
                            "bs": "4",
                            "pos": "P",
                            "id": "572096",
                            "name": "Rosenthal",
                            "bf": "4",
                            "sv": "14",
                            "bb": "1",
                            "hld": "0",
                            "so": "1",
                            "s_so": "51",
                            "l": "4",
                            "h": "0",
                            "s_ip": "36.1",
                            "w": "2",
                            "s_bb": "28",
                            "s_r": "22",
                            "s": "10",
                            "r": "0",
                            "er": "0",
                            "out": "3"
                        },
                        {
                            "hr": "0",
                            "s_er": "6",
                            "np": "21",
                            "name_display_first_last": "Sam Tuivailala",
                            "s_h": "12",
                            "era": "6.75",
                            "game_score": "40",
                            "bs": "0",
                            "pos": "P",
                            "id": "592815",
                            "name": "Tuivailala",
                            "bf": "4",
                            "sv": "0",
                            "bb": "2",
                            "hld": "0",
                            "so": "0",
                            "s_so": "7",
                            "l": "0",
                            "h": "0",
                            "s_ip": "8.0",
                            "w": "0",
                            "s_bb": "6",
                            "s_r": "6",
                            "s": "9",
                            "r": "0",
                            "er": "0",
                            "out": "2"
                        },
                        {
                            "hr": "0",
                            "s_er": "14",
                            "np": "5",
                            "name_display_first_last": "Zach Duke",
                            "s_h": "44",
                            "era": "2.15",
                            "game_score": "43",
                            "bs": "3",
                            "pos": "P",
                            "id": "435043",
                            "name": "Duke",
                            "bf": "1",
                            "sv": "2",
                            "bb": "0",
                            "hld": "24",
                            "so": "1",
                            "s_so": "65",
                            "l": "1",
                            "h": "0",
                            "s_ip": "58.2",
                            "w": "2",
                            "s_bb": "27",
                            "s_r": "14",
                            "s": "3",
                            "r": "0",
                            "er": "0",
                            "out": "1"
                        },
                        {
                            "hr": "0",
                            "s_er": "11",
                            "np": "24",
                            "name_display_first_last": "Jerome Williams",
                            "s_h": "21",
                            "era": "6.06",
                            "game_score": "45",
                            "bs": "0",
                            "pos": "P",
                            "id": "425532",
                            "name": "Williams, J",
                            "bf": "4",
                            "sv": "0",
                            "bb": "0",
                            "hld": "0",
                            "so": "1",
                            "s_so": "8",
                            "l": "0",
                            "h": "1",
                            "s_ip": "16.1",
                            "w": "0",
                            "s_bb": "6",
                            "s_r": "15",
                            "s": "14",
                            "r": "0",
                            "er": "0",
                            "out": "3"
                        }
                    ],
                    "bf": "39",
                    "era": "4.06",
                    "team_flag": "away",
                    "bb": "6",
                    "er": "5",
                    "h": "9",
                    "out": "24"
                },
                {
                    "hr": "0",
                    "so": "13",
                    "r": "0",
                    "pitcher": [
                        {
                            "hr": "0",
                            "s_er": "61",
                            "np": "99",
                            "name_display_first_last": "Jake Arrieta",
                            "s_h": "128",
                            "era": "2.85",
                            "game_score": "80",
                            "bs": "0",
                            "pos": "P",
                            "id": "453562",
                            "name": "Arrieta",
                            "bf": "24",
                            "sv": "0",
                            "bb": "1",
                            "note": "(W, 18-7)",
                            "hld": "0",
                            "so": "10",
                            "s_so": "186",
                            "l": "7",
                            "win": "true",
                            "h": "5",
                            "s_ip": "192.1",
                            "w": "18",
                            "s_bb": "74",
                            "s_r": "65",
                            "s": "68",
                            "r": "0",
                            "er": "0",
                            "out": "21"
                        },
                        {
                            "hr": "0",
                            "s_er": "14",
                            "np": "13",
                            "name_display_first_last": "Pedro Strop",
                            "s_h": "26",
                            "era": "2.82",
                            "game_score": "45",
                            "bs": "4",
                            "pos": "P",
                            "id": "467008",
                            "name": "Strop",
                            "bf": "3",
                            "sv": "0",
                            "bb": "1",
                            "hld": "21",
                            "so": "1",
                            "s_so": "57",
                            "l": "2",
                            "h": "0",
                            "s_ip": "44.2",
                            "w": "2",
                            "s_bb": "14",
                            "s_r": "15",
                            "s": "6",
                            "r": "0",
                            "er": "0",
                            "out": "3"
                        },
                        {
                            "hr": "0",
                            "s_er": "20",
                            "np": "7",
                            "name_display_first_last": "Travis Wood",
                            "s_h": "45",
                            "era": "3.10",
                            "game_score": "43",
                            "bs": "1",
                            "pos": "P",
                            "id": "475243",
                            "name": "Wood, T",
                            "bf": "1",
                            "sv": "0",
                            "bb": "0",
                            "hld": "11",
                            "so": "1",
                            "s_so": "45",
                            "l": "0",
                            "h": "0",
                            "s_ip": "58.0",
                            "w": "4",
                            "s_bb": "23",
                            "s_r": "24",
                            "s": "4",
                            "r": "0",
                            "er": "0",
                            "out": "1"
                        },
                        {
                            "hr": "0",
                            "s_er": "12",
                            "np": "8",
                            "name_display_first_last": "Carl Edwards Jr.",
                            "s_h": "14",
                            "era": "3.31",
                            "game_score": "45",
                            "bs": "1",
                            "pos": "P",
                            "id": "605218",
                            "name": "Edwards Jr.",
                            "bf": "2",
                            "sv": "1",
                            "bb": "0",
                            "hld": "4",
                            "so": "1",
                            "s_so": "47",
                            "l": "1",
                            "h": "0",
                            "s_ip": "32.2",
                            "w": "0",
                            "s_bb": "12",
                            "s_r": "12",
                            "s": "7",
                            "r": "0",
                            "er": "0",
                            "out": "2"
                        }
                    ],
                    "bf": "30",
                    "era": "3.07",
                    "team_flag": "home",
                    "bb": "2",
                    "er": "0",
                    "h": "5",
                    "out": "27"
                }
            ],
            "home_id": "112",
            "away_loss": "73",
            "game_info_es": "\n      <relief_no_out>Kiekhefer enfrentó 1 bateador en la 4th.</relief_no_out><br/><br/>\n      <game_score>Leake 26; Arrieta 80.</game_score><br/>\n      <wild_pitches>Leake 2.</wild_pitches><br/>\n      <pitches_to_strikes>Leake 77-44; Kiekhefer 5-3; Socolovich 21-13; Rosenthal 14-10; Tuivailala 21-9; Duke 5-3; Williams, J 24-14; Arrieta 99-68; Strop 13-6; Wood, T 7-4; Edwards Jr. 8-7.</pitches_to_strikes><br/>\n      <groundouts_to_flyouts>Leake 3-4; Kiekhefer 0-0; Socolovich 5-0; Rosenthal 1-0; Tuivailala 1-0; Duke 0-0; Williams, J 0-2; Arrieta 5-2; Strop 1-0; Wood, T 0-0; Edwards Jr. 0-1.</groundouts_to_flyouts><br/>\n      <batters_faced>Leake 20; Kiekhefer 1; Socolovich 5; Rosenthal 4; Tuivailala 4; Duke 1; Williams, J 4; Arrieta 24; Strop 3; Wood, T 1; Edwards Jr. 2.</batters_faced><br/>\n      <inherited_runners_scored>Kiekhefer 2-0; Socolovich 3-1; Duke 2-0.</inherited_runners_scored><br/>\n      <umpires>\n         <umpire id=\"427044\" position=\"HP\" name=\"CB Bucknor\"></umpire>\n         <umpire id=\"427424\" position=\"1B\" name=\"Jim Reynolds\"></umpire>\n         <umpire id=\"427090\" position=\"2B\" name=\"Fieldin Culbreth\"></umpire>\n         <umpire id=\"484499\" position=\"3B\" name=\"Manny Gonzalez\"></umpire>\n      </umpires>\n      <weather>71 degrees, overcast</weather>\n      <wind>9 mph, In from LF</wind>\n      <weather>1:22 PM</weather>\n      <time>2:53</time>\n      <attendance>40,791</attendance>\n      <wind>Wrigley Field</wind>\n      <wind>September 23, 2016</wind>",
            "batting": [
                {
                    "hr": "0",
                    "d": "3",
                    "da": "10",
                    "so": "4",
                    "batter": [
                        {
                            "hr": "0",
                            "sac": "0",
                            "name_display_first_last": "Dexter Fowler",
                            "s_h": "118",
                            "s_hr": "13",
                            "s_rbi": "46",
                            "pos": "CF",
                            "id": "451594",
                            "rbi": "0",
                            "bo": "100",
                            "lob": "2",
                            "name": "Fowler",
                            "slg": ".441",
                            "avg": ".271",
                            "bb": "1",
                            "fldg": "1.000",
                            "ops": ".827",
                            "hbp": "0",
                            "d": "0",
                            "e": "0",
                            "so": "0",
                            "a": "0",
                            "s_so": "118",
                            "sf": "0",
                            "h": "0",
                            "cs": "0",
                            "obp": ".386",
                            "s_bb": "73",
                            "s_r": "80",
                            "t": "0",
                            "ao": "3",
                            "r": "1",
                            "sb": "0",
                            "po": "2",
                            "ab": "4",
                            "go": "1"
                        },
                        {
                            "hr": "0",
                            "sac": "0",
                            "name_display_first_last": "Kris Bryant",
                            "s_h": "172",
                            "s_hr": "38",
                            "s_rbi": "99",
                            "pos": "3B",
                            "id": "592178",
                            "rbi": "0",
                            "bo": "200",
                            "lob": "1",
                            "name": "Bryant",
                            "slg": ".564",
                            "avg": ".297",
                            "bb": "1",
                            "fldg": "1.000",
                            "ops": ".952",
                            "hbp": "0",
                            "d": "0",
                            "e": "0",
                            "so": "0",
                            "a": "3",
                            "s_so": "147",
                            "sf": "0",
                            "h": "2",
                            "cs": "0",
                            "obp": ".388",
                            "s_bb": "71",
                            "s_r": "118",
                            "t": "0",
                            "ao": "1",
                            "r": "1",
                            "sb": "0",
                            "po": "1",
                            "ab": "4",
                            "go": "1"
                        },
                        {
                            "hr": "0",
                            "sac": "0",
                            "name_display_first_last": "Anthony Rizzo",
                            "s_h": "164",
                            "s_hr": "31",
                            "s_rbi": "105",
                            "pos": "1B",
                            "id": "519203",
                            "rbi": "1",
                            "bo": "300",
                            "lob": "2",
                            "name": "Rizzo",
                            "slg": ".552",
                            "avg": ".295",
                            "bb": "0",
                            "fldg": "1.000",
                            "ops": ".942",
                            "hbp": "0",
                            "d": "2",
                            "e": "0",
                            "so": "1",
                            "a": "1",
                            "s_so": "101",
                            "sf": "0",
                            "h": "3",
                            "cs": "0",
                            "obp": ".390",
                            "s_bb": "73",
                            "s_r": "90",
                            "t": "0",
                            "ao": "1",
                            "r": "1",
                            "sb": "0",
                            "po": "6",
                            "ab": "5"
                        },
                        {
                            "hr": "0",
                            "sac": "0",
                            "name_display_first_last": "Ben Zobrist",
                            "s_h": "134",
                            "s_hr": "15",
                            "s_rbi": "70",
                            "pos": "2B-LF",
                            "id": "450314",
                            "rbi": "2",
                            "bo": "400",
                            "lob": "3",
                            "name": "Zobrist",
                            "slg": ".422",
                            "avg": ".267",
                            "bb": "1",
                            "fldg": "1.000",
                            "ops": ".803",
                            "hbp": "0",
                            "d": "0",
                            "e": "0",
                            "so": "0",
                            "a": "2",
                            "s_so": "79",
                            "sf": "0",
                            "h": "1",
                            "cs": "0",
                            "obp": ".381",
                            "s_bb": "91",
                            "s_r": "88",
                            "t": "0",
                            "ao": "1",
                            "r": "0",
                            "sb": "1",
                            "po": "2",
                            "ab": "3",
                            "go": "1"
                        },
                        {
                            "hr": "0",
                            "sac": "0",
                            "name_display_first_last": "Addison Russell",
                            "s_h": "122",
                            "s_hr": "21",
                            "s_rbi": "93",
                            "pos": "SS",
                            "id": "608365",
                            "rbi": "0",
                            "bo": "500",
                            "lob": "5",
                            "name": "Russell",
                            "slg": ".426",
                            "avg": ".243",
                            "bb": "0",
                            "fldg": "1.000",
                            "ops": ".749",
                            "hbp": "0",
                            "d": "0",
                            "e": "0",
                            "so": "0",
                            "a": "2",
                            "s_so": "128",
                            "sf": "0",
                            "h": "0",
                            "cs": "0",
                            "obp": ".323",
                            "s_bb": "52",
                            "s_r": "63",
                            "t": "0",
                            "ao": "2",
                            "r": "0",
                            "sb": "0",
                            "po": "1",
                            "ab": "4",
                            "go": "2"
                        },
                        {
                            "hr": "0",
                            "sac": "0",
                            "name_display_first_last": "Jason Heyward",
                            "s_h": "117",
                            "s_hr": "7",
                            "s_rbi": "45",
                            "pos": "RF",
                            "id": "518792",
                            "rbi": "0",
                            "bo": "600",
                            "lob": "2",
                            "name": "Heyward",
                            "slg": ".323",
                            "avg": ".230",
                            "bb": "1",
                            "fldg": "1.000",
                            "ops": ".628",
                            "hbp": "0",
                            "d": "0",
                            "e": "0",
                            "so": "0",
                            "a": "0",
                            "s_so": "89",
                            "sf": "0",
                            "h": "0",
                            "cs": "0",
                            "obp": ".305",
                            "s_bb": "50",
                            "s_r": "57",
                            "t": "0",
                            "ao": "0",
                            "r": "1",
                            "sb": "1",
                            "po": "2",
                            "ab": "3",
                            "go": "3"
                        },
                        {
                            "hr": "0",
                            "sac": "0",
                            "name_display_first_last": "Chris Coghlan",
                            "s_h": "45",
                            "s_hr": "6",
                            "s_rbi": "27",
                            "pos": "LF",
                            "id": "458085",
                            "rbi": "1",
                            "bo": "700",
                            "lob": "0",
                            "name": "Coghlan",
                            "slg": ".314",
                            "avg": ".184",
                            "bb": "2",
                            "fldg": ".000",
                            "ops": ".594",
                            "hbp": "0",
                            "d": "1",
                            "e": "0",
                            "so": "0",
                            "a": "0",
                            "s_so": "72",
                            "sf": "0",
                            "h": "1",
                            "cs": "0",
                            "obp": ".280",
                            "s_bb": "30",
                            "s_r": "33",
                            "t": "0",
                            "ao": "0",
                            "r": "0",
                            "sb": "0",
                            "po": "0",
                            "ab": "2",
                            "go": "1"
                        },
                        {
                            "hr": "0",
                            "sac": "0",
                            "name_display_first_last": "Javier Baez",
                            "s_h": "109",
                            "s_hr": "13",
                            "s_rbi": "51",
                            "pos": "2B",
                            "id": "595879",
                            "rbi": "0",
                            "bo": "701",
                            "lob": "0",
                            "name": "Baez, J",
                            "slg": ".424",
                            "avg": ".273",
                            "bb": "0",
                            "fldg": ".000",
                            "ops": ".737",
                            "hbp": "0",
                            "d": "0",
                            "e": "0",
                            "so": "0",
                            "a": "0",
                            "s_so": "102",
                            "sf": "0",
                            "h": "0",
                            "cs": "0",
                            "obp": ".313",
                            "s_bb": "15",
                            "s_r": "48",
                            "t": "0",
                            "ao": "0",
                            "r": "0",
                            "sb": "0",
                            "po": "0",
                            "ab": "0"
                        },
                        {
                            "hr": "0",
                            "sac": "0",
                            "name_display_first_last": "Miguel Montero",
                            "s_h": "50",
                            "s_hr": "7",
                            "s_rbi": "31",
                            "pos": "C",
                            "id": "471083",
                            "rbi": "0",
                            "bo": "800",
                            "lob": "4",
                            "name": "Montero",
                            "slg": ".352",
                            "avg": ".217",
                            "bb": "0",
                            "fldg": "1.000",
                            "ops": ".680",
                            "hbp": "0",
                            "d": "0",
                            "e": "0",
                            "so": "1",
                            "a": "1",
                            "s_so": "56",
                            "sf": "0",
                            "h": "0",
                            "cs": "0",
                            "obp": ".328",
                            "s_bb": "36",
                            "s_r": "30",
                            "t": "0",
                            "ao": "1",
                            "r": "0",
                            "sb": "0",
                            "po": "10",
                            "ab": "3",
                            "go": "1"
                        },
                        {
                            "hr": "0",
                            "sac": "0",
                            "name_display_first_last": "Jorge Soler",
                            "s_h": "54",
                            "s_hr": "12",
                            "s_rbi": "31",
                            "pos": "PH",
                            "id": "624585",
                            "rbi": "0",
                            "bo": "801",
                            "lob": "2",
                            "name": "Soler",
                            "slg": ".446",
                            "avg": ".243",
                            "bb": "0",
                            "fldg": ".000",
                            "note": "a-",
                            "ops": ".781",
                            "hbp": "0",
                            "d": "0",
                            "e": "0",
                            "so": "1",
                            "a": "0",
                            "s_so": "66",
                            "sf": "0",
                            "h": "0",
                            "cs": "0",
                            "obp": ".335",
                            "s_bb": "29",
                            "s_r": "36",
                            "t": "0",
                            "ao": "0",
                            "r": "0",
                            "sb": "0",
                            "po": "0",
                            "ab": "1"
                        },
                        {
                            "hr": "0",
                            "sac": "0",
                            "name_display_first_last": "Pedro Strop",
                            "s_h": "0",
                            "s_hr": "0",
                            "s_rbi": "0",
                            "pos": "P",
                            "id": "467008",
                            "rbi": "0",
                            "bo": "802",
                            "lob": "0",
                            "name": "Strop",
                            "slg": ".000",
                            "avg": ".000",
                            "bb": "0",
                            "fldg": ".000",
                            "ops": ".000",
                            "hbp": "0",
                            "d": "0",
                            "e": "0",
                            "so": "0",
                            "a": "0",
                            "s_so": "0",
                            "sf": "0",
                            "h": "0",
                            "cs": "0",
                            "obp": ".000",
                            "s_bb": "0",
                            "s_r": "0",
                            "t": "0",
                            "ao": "0",
                            "r": "0",
                            "sb": "0",
                            "po": "0",
                            "ab": "0"
                        },
                        {
                            "hr": "0",
                            "sac": "0",
                            "name_display_first_last": "Travis Wood",
                            "s_h": "2",
                            "s_hr": "0",
                            "s_rbi": "1",
                            "pos": "P",
                            "id": "475243",
                            "rbi": "0",
                            "bo": "803",
                            "lob": "0",
                            "name": "Wood, T",
                            "slg": ".222",
                            "avg": ".222",
                            "bb": "0",
                            "fldg": ".000",
                            "ops": ".522",
                            "hbp": "0",
                            "d": "0",
                            "e": "0",
                            "so": "0",
                            "a": "0",
                            "s_so": "3",
                            "sf": "0",
                            "h": "0",
                            "cs": "0",
                            "obp": ".300",
                            "s_bb": "1",
                            "s_r": "0",
                            "t": "0",
                            "ao": "0",
                            "r": "0",
                            "sb": "0",
                            "po": "0",
                            "ab": "0"
                        },
                        {
                            "hr": "0",
                            "sac": "0",
                            "name_display_first_last": "Carl Edwards Jr.",
                            "s_h": "0",
                            "s_hr": "0",
                            "s_rbi": "0",
                            "pos": "P",
                            "id": "605218",
                            "rbi": "0",
                            "bo": "804",
                            "lob": "0",
                            "name": "Edwards Jr.",
                            "slg": ".000",
                            "avg": ".000",
                            "bb": "0",
                            "fldg": ".000",
                            "ops": ".000",
                            "hbp": "0",
                            "d": "0",
                            "e": "0",
                            "so": "0",
                            "a": "0",
                            "s_so": "1",
                            "sf": "0",
                            "h": "0",
                            "cs": "0",
                            "obp": ".000",
                            "s_bb": "0",
                            "s_r": "0",
                            "t": "0",
                            "ao": "0",
                            "r": "0",
                            "sb": "0",
                            "po": "0",
                            "ab": "0"
                        },
                        {
                            "hr": "0",
                            "sac": "0",
                            "name_display_first_last": "Jake Arrieta",
                            "s_h": "17",
                            "s_hr": "2",
                            "s_rbi": "7",
                            "pos": "P",
                            "id": "453562",
                            "rbi": "0",
                            "bo": "900",
                            "lob": "0",
                            "name": "Arrieta",
                            "slg": ".429",
                            "avg": ".270",
                            "bb": "0",
                            "fldg": "1.000",
                            "ops": ".742",
                            "hbp": "0",
                            "d": "0",
                            "e": "0",
                            "so": "1",
                            "a": "1",
                            "s_so": "28",
                            "sf": "0",
                            "h": "1",
                            "cs": "0",
                            "obp": ".313",
                            "s_bb": "4",
                            "s_r": "7",
                            "t": "0",
                            "ao": "1",
                            "r": "1",
                            "sb": "0",
                            "po": "0",
                            "ab": "3"
                        },
                        {
                            "hr": "0",
                            "sac": "0",
                            "name_display_first_last": "Willson Contreras",
                            "s_h": "62",
                            "s_hr": "10",
                            "s_rbi": "31",
                            "pos": "C",
                            "id": "575929",
                            "rbi": "0",
                            "bo": "901",
                            "lob": "0",
                            "name": "Contreras",
                            "slg": ".459",
                            "avg": ".266",
                            "bb": "0",
                            "fldg": "1.000",
                            "ops": ".803",
                            "hbp": "0",
                            "d": "0",
                            "e": "0",
                            "so": "0",
                            "a": "0",
                            "s_so": "61",
                            "sf": "0",
                            "h": "1",
                            "cs": "0",
                            "obp": ".344",
                            "s_bb": "24",
                            "s_r": "29",
                            "t": "0",
                            "ao": "0",
                            "r": "0",
                            "sb": "0",
                            "po": "3",
                            "ab": "1"
                        }
                    ],
                    "h": "9",
                    "text_data_es": "\n         <doubles>Rizzo 2 (42, Leake, Leake); Coghlan (12, Leake).</doubles><br/>\n         <total_bases>Contreras; Arrieta; Zobrist; Bryant 2; Rizzo 5; Coghlan 2.</total_bases><br/>\n         <rbi>Rizzo (105); Zobrist 2 (70); Coghlan (27).</rbi><br/>\n         <two_out_rbi>Coghlan.</two_out_rbi><br/>\n         <risp_lob_two_out>Montero 3; Russell 2; Soler.</risp_lob_two_out><br/>\n         <team_risp>\n            \t\t\t\t\t\t\tde 3-10.\n         </team_risp>\n         <team_lob>10.</team_lob>\n         <stolen_bases>Heyward (9, 2nd base a Leake/Molina); Zobrist (6, 2nd base a Socolovich/Molina).</stolen_bases><br/>\n         <double_plays>3 (Bryant-Zobrist-Rizzo; Rizzo-Bryant-Zobrist; Bryant-Russell-Rizzo).</double_plays><br/>\n         <pickoffs>Montero (Adams, M en 1st base).</pickoffs><br/><br/>",
                    "note_es": "\n         <pinch_hitters>a-Bateó por Montero en la 7th. </pinch_hitters>",
                    "text_data": "\n         <doubles>Rizzo 2 (42, Leake, Leake); Coghlan (12, Leake).</doubles><br/>\n         <total_bases>Contreras; Arrieta; Zobrist; Bryant 2; Rizzo 5; Coghlan 2.</total_bases><br/>\n         <rbi>Rizzo (105); Zobrist 2 (70); Coghlan (27).</rbi><br/>\n         <two_out_rbi>Coghlan.</two_out_rbi><br/>\n         <risp_lob_two_out>Montero 3; Russell 2; Soler.</risp_lob_two_out><br/>\n         <team_risp>3-for-10.</team_risp>\n         <team_lob>10.</team_lob>\n         <stolen_bases>Heyward (9, 2nd base off Leake/Molina); Zobrist (6, 2nd base off Socolovich/Molina).</stolen_bases><br/>\n         <double_plays>3 (Bryant-Zobrist-Rizzo; Rizzo-Bryant-Zobrist; Bryant-Russell-Rizzo).</double_plays><br/>\n         <pickoffs>Montero (Adams, M at 1st base).</pickoffs><br/><br/>",
                    "obp": ".343",
                    "rbi": "4",
                    "lob": "21",
                    "t": "0",
                    "r": "5",
                    "team_flag": "home",
                    "ab": "33",
                    "po": "27",
                    "slg": ".428",
                    "avg": ".256",
                    "bb": "6",
                    "note": "\n         <pinch_hitters>a-Struck out for Montero in the 7th. </pinch_hitters>",
                    "ops": ".771"
                },
                {
                    "hr": "0",
                    "d": "0",
                    "da": "9",
                    "so": "13",
                    "batter": [
                        {
                            "hr": "0",
                            "sac": "0",
                            "name_display_first_last": "Matt Carpenter",
                            "s_h": "122",
                            "s_hr": "19",
                            "s_rbi": "62",
                            "pos": "2B",
                            "id": "572761",
                            "rbi": "0",
                            "bo": "100",
                            "lob": "2",
                            "name": "Carpenter",
                            "slg": ".503",
                            "avg": ".273",
                            "bb": "0",
                            "fldg": "1.000",
                            "ops": ".883",
                            "hbp": "0",
                            "d": "0",
                            "e": "0",
                            "so": "3",
                            "a": "5",
                            "s_so": "101",
                            "sf": "0",
                            "h": "0",
                            "cs": "0",
                            "obp": ".380",
                            "s_bb": "73",
                            "s_r": "77",
                            "t": "0",
                            "ao": "1",
                            "r": "0",
                            "sb": "0",
                            "po": "3",
                            "ab": "4"
                        },
                        {
                            "hr": "0",
                            "sac": "0",
                            "name_display_first_last": "Jedd Gyorko",
                            "s_h": "91",
                            "s_hr": "27",
                            "s_rbi": "54",
                            "pos": "SS",
                            "id": "576397",
                            "rbi": "0",
                            "bo": "200",
                            "lob": "1",
                            "name": "Gyorko",
                            "slg": ".484",
                            "avg": ".241",
                            "bb": "0",
                            "fldg": "1.000",
                            "ops": ".787",
                            "hbp": "0",
                            "d": "0",
                            "e": "0",
                            "so": "2",
                            "a": "2",
                            "s_so": "88",
                            "sf": "0",
                            "h": "0",
                            "cs": "0",
                            "obp": ".303",
                            "s_bb": "34",
                            "s_r": "53",
                            "t": "0",
                            "ao": "1",
                            "r": "0",
                            "sb": "0",
                            "po": "5",
                            "ab": "4",
                            "go": "1"
                        },
                        {
                            "hr": "0",
                            "sac": "0",
                            "name_display_first_last": "Stephen Piscotty",
                            "s_h": "148",
                            "s_hr": "21",
                            "s_rbi": "81",
                            "pos": "RF",
                            "id": "572039",
                            "rbi": "0",
                            "bo": "300",
                            "lob": "0",
                            "name": "Piscotty",
                            "slg": ".453",
                            "avg": ".270",
                            "bb": "0",
                            "fldg": "1.000",
                            "ops": ".794",
                            "hbp": "0",
                            "d": "0",
                            "e": "0",
                            "so": "2",
                            "a": "0",
                            "s_so": "128",
                            "sf": "0",
                            "h": "0",
                            "cs": "0",
                            "obp": ".341",
                            "s_bb": "49",
                            "s_r": "80",
                            "t": "0",
                            "ao": "1",
                            "r": "0",
                            "sb": "0",
                            "po": "2",
                            "ab": "4",
                            "go": "1"
                        },
                        {
                            "hr": "0",
                            "sac": "0",
                            "name_display_first_last": "Matt Adams",
                            "s_h": "72",
                            "s_hr": "15",
                            "s_rbi": "50",
                            "pos": "1B",
                            "id": "571431",
                            "rbi": "0",
                            "bo": "400",
                            "lob": "0",
                            "name": "Adams, M",
                            "slg": ".469",
                            "avg": ".252",
                            "bb": "1",
                            "fldg": "1.000",
                            "ops": ".781",
                            "hbp": "0",
                            "d": "0",
                            "e": "0",
                            "so": "1",
                            "a": "0",
                            "s_so": "78",
                            "sf": "0",
                            "h": "1",
                            "cs": "0",
                            "obp": ".312",
                            "s_bb": "25",
                            "s_r": "35",
                            "t": "0",
                            "ao": "0",
                            "r": "0",
                            "sb": "0",
                            "po": "6",
                            "ab": "2"
                        },
                        {
                            "hr": "0",
                            "gidp": "1",
                            "sac": "0",
                            "name_display_first_last": "Yadier Molina",
                            "s_h": "148",
                            "s_hr": "7",
                            "s_rbi": "49",
                            "pos": "C",
                            "id": "425877",
                            "rbi": "0",
                            "bo": "500",
                            "lob": "1",
                            "name": "Molina",
                            "slg": ".408",
                            "avg": ".296",
                            "bb": "0",
                            "fldg": "1.000",
                            "ops": ".759",
                            "hbp": "0",
                            "d": "0",
                            "e": "0",
                            "so": "1",
                            "a": "0",
                            "s_so": "61",
                            "sf": "0",
                            "h": "1",
                            "cs": "0",
                            "obp": ".351",
                            "s_bb": "39",
                            "s_r": "50",
                            "t": "0",
                            "ao": "0",
                            "r": "0",
                            "sb": "0",
                            "po": "4",
                            "ab": "3",
                            "go": "2"
                        },
                        {
                            "hr": "0",
                            "sac": "0",
                            "name_display_first_last": "Randal Grichuk",
                            "s_h": "100",
                            "s_hr": "23",
                            "s_rbi": "62",
                            "pos": "CF",
                            "id": "545341",
                            "rbi": "0",
                            "bo": "600",
                            "lob": "1",
                            "name": "Grichuk",
                            "slg": ".491",
                            "avg": ".243",
                            "bb": "0",
                            "fldg": "1.000",
                            "ops": ".784",
                            "hbp": "0",
                            "d": "0",
                            "e": "0",
                            "so": "3",
                            "a": "0",
                            "s_so": "127",
                            "sf": "0",
                            "h": "0",
                            "cs": "0",
                            "obp": ".293",
                            "s_bb": "26",
                            "s_r": "62",
                            "t": "0",
                            "ao": "0",
                            "r": "0",
                            "sb": "0",
                            "po": "3",
                            "ab": "3"
                        },
                        {
                            "hr": "0",
                            "sac": "0",
                            "name_display_first_last": "Jhonny Peralta",
                            "s_h": "62",
                            "s_hr": "7",
                            "s_rbi": "24",
                            "pos": "3B",
                            "id": "425509",
                            "rbi": "0",
                            "bo": "700",
                            "lob": "0",
                            "name": "Peralta, J",
                            "slg": ".392",
                            "avg": ".243",
                            "bb": "1",
                            "fldg": "1.000",
                            "ops": ".682",
                            "hbp": "0",
                            "d": "0",
                            "e": "0",
                            "so": "0",
                            "a": "2",
                            "s_so": "51",
                            "sf": "0",
                            "h": "1",
                            "cs": "0",
                            "obp": ".290",
                            "s_bb": "17",
                            "s_r": "29",
                            "t": "0",
                            "ao": "1",
                            "r": "0",
                            "sb": "0",
                            "po": "0",
                            "ab": "2"
                        },
                        {
                            "hr": "0",
                            "sac": "0",
                            "name_display_first_last": "Kolten Wong",
                            "s_h": "74",
                            "s_hr": "5",
                            "s_rbi": "23",
                            "pos": "LF",
                            "id": "543939",
                            "rbi": "0",
                            "bo": "800",
                            "lob": "1",
                            "name": "Wong",
                            "slg": ".347",
                            "avg": ".238",
                            "bb": "0",
                            "fldg": "1.000",
                            "ops": ".673",
                            "hbp": "0",
                            "d": "0",
                            "e": "0",
                            "so": "1",
                            "a": "0",
                            "s_so": "52",
                            "sf": "0",
                            "h": "1",
                            "cs": "0",
                            "obp": ".326",
                            "s_bb": "34",
                            "s_r": "39",
                            "t": "0",
                            "ao": "0",
                            "r": "0",
                            "sb": "0",
                            "po": "1",
                            "ab": "3",
                            "go": "1"
                        },
                        {
                            "hr": "0",
                            "gidp": "1",
                            "sac": "0",
                            "name_display_first_last": "Mike Leake",
                            "s_h": "7",
                            "s_hr": "0",
                            "s_rbi": "4",
                            "pos": "P",
                            "id": "502190",
                            "rbi": "0",
                            "bo": "900",
                            "lob": "2",
                            "name": "Leake",
                            "slg": ".167",
                            "avg": ".146",
                            "bb": "0",
                            "fldg": ".000",
                            "ops": ".363",
                            "hbp": "0",
                            "d": "0",
                            "e": "0",
                            "so": "0",
                            "a": "0",
                            "s_so": "19",
                            "sf": "0",
                            "h": "0",
                            "cs": "0",
                            "obp": ".196",
                            "s_bb": "3",
                            "s_r": "3",
                            "t": "0",
                            "ao": "0",
                            "r": "0",
                            "sb": "0",
                            "po": "0",
                            "ab": "1",
                            "go": "2"
                        },
                        {
                            "hr": "0",
                            "sac": "0",
                            "name_display_first_last": "Dean Kiekhefer",
                            "s_h": "0",
                            "s_hr": "0",
                            "s_rbi": "0",
                            "pos": "P",
                            "id": "518883",
                            "rbi": "0",
                            "bo": "901",
                            "lob": "0",
                            "name": "Kiekhefer",
                            "slg": ".000",
                            "avg": ".000",
                            "bb": "0",
                            "fldg": ".000",
                            "ops": ".000",
                            "hbp": "0",
                            "d": "0",
                            "e": "0",
                            "so": "0",
                            "a": "0",
                            "s_so": "0",
                            "sf": "0",
                            "h": "0",
                            "cs": "0",
                            "obp": ".000",
                            "s_bb": "0",
                            "s_r": "0",
                            "t": "0",
                            "ao": "0",
                            "r": "0",
                            "sb": "0",
                            "po": "0",
                            "ab": "0"
                        },
                        {
                            "hr": "0",
                            "sac": "0",
                            "name_display_first_last": "Miguel Socolovich",
                            "s_h": "0",
                            "s_hr": "0",
                            "s_rbi": "0",
                            "pos": "P",
                            "id": "462515",
                            "rbi": "0",
                            "bo": "902",
                            "lob": "0",
                            "name": "Socolovich",
                            "slg": ".000",
                            "avg": ".000",
                            "bb": "0",
                            "fldg": ".000",
                            "ops": ".000",
                            "hbp": "0",
                            "d": "0",
                            "e": "0",
                            "so": "0",
                            "a": "0",
                            "s_so": "0",
                            "sf": "0",
                            "h": "0",
                            "cs": "0",
                            "obp": ".000",
                            "s_bb": "0",
                            "s_r": "0",
                            "t": "0",
                            "ao": "0",
                            "r": "0",
                            "sb": "0",
                            "po": "0",
                            "ab": "0"
                        },
                        {
                            "hr": "0",
                            "sac": "0",
                            "name_display_first_last": "Greg Garcia",
                            "s_h": "54",
                            "s_hr": "3",
                            "s_rbi": "17",
                            "pos": "PH",
                            "id": "594824",
                            "rbi": "0",
                            "bo": "903",
                            "lob": "0",
                            "name": "Garcia, G",
                            "slg": ".368",
                            "avg": ".269",
                            "bb": "0",
                            "fldg": ".000",
                            "note": "a-",
                            "ops": ".759",
                            "hbp": "0",
                            "d": "0",
                            "e": "0",
                            "so": "0",
                            "a": "0",
                            "s_so": "46",
                            "sf": "0",
                            "h": "1",
                            "cs": "0",
                            "obp": ".391",
                            "s_bb": "37",
                            "s_r": "32",
                            "t": "0",
                            "ao": "0",
                            "r": "0",
                            "sb": "0",
                            "po": "0",
                            "ab": "1"
                        },
                        {
                            "hr": "0",
                            "sac": "0",
                            "name_display_first_last": "Trevor Rosenthal",
                            "s_h": "0",
                            "s_hr": "0",
                            "s_rbi": "0",
                            "pos": "P",
                            "id": "572096",
                            "rbi": "0",
                            "bo": "904",
                            "lob": "0",
                            "name": "Rosenthal",
                            "slg": ".000",
                            "avg": ".000",
                            "bb": "0",
                            "fldg": ".000",
                            "ops": ".000",
                            "hbp": "0",
                            "d": "0",
                            "e": "0",
                            "so": "0",
                            "a": "0",
                            "s_so": "1",
                            "sf": "0",
                            "h": "0",
                            "cs": "0",
                            "obp": ".000",
                            "s_bb": "0",
                            "s_r": "0",
                            "t": "0",
                            "ao": "0",
                            "r": "0",
                            "sb": "0",
                            "po": "0",
                            "ab": "0"
                        },
                        {
                            "hr": "0",
                            "sac": "0",
                            "name_display_first_last": "Sam Tuivailala",
                            "s_h": "0",
                            "s_hr": "0",
                            "s_rbi": "0",
                            "pos": "P",
                            "id": "592815",
                            "rbi": "0",
                            "bo": "905",
                            "lob": "0",
                            "name": "Tuivailala",
                            "slg": ".000",
                            "avg": ".000",
                            "bb": "0",
                            "fldg": ".000",
                            "ops": ".000",
                            "hbp": "0",
                            "d": "0",
                            "e": "0",
                            "so": "0",
                            "a": "0",
                            "s_so": "0",
                            "sf": "0",
                            "h": "0",
                            "cs": "0",
                            "obp": ".000",
                            "s_bb": "0",
                            "s_r": "0",
                            "t": "0",
                            "ao": "0",
                            "r": "0",
                            "sb": "0",
                            "po": "0",
                            "ab": "0"
                        },
                        {
                            "hr": "0",
                            "sac": "0",
                            "name_display_first_last": "Zach Duke",
                            "s_h": "0",
                            "s_hr": "0",
                            "s_rbi": "0",
                            "pos": "P",
                            "id": "435043",
                            "rbi": "0",
                            "bo": "906",
                            "lob": "0",
                            "name": "Duke",
                            "slg": ".000",
                            "avg": ".000",
                            "bb": "0",
                            "fldg": ".000",
                            "ops": ".000",
                            "hbp": "0",
                            "d": "0",
                            "e": "0",
                            "so": "0",
                            "a": "0",
                            "s_so": "0",
                            "sf": "0",
                            "h": "0",
                            "cs": "0",
                            "obp": ".000",
                            "s_bb": "0",
                            "s_r": "0",
                            "t": "0",
                            "ao": "0",
                            "r": "0",
                            "sb": "0",
                            "po": "0",
                            "ab": "0"
                        },
                        {
                            "hr": "0",
                            "gidp": "1",
                            "sac": "0",
                            "name_display_first_last": "Brandon Moss",
                            "s_h": "89",
                            "s_hr": "27",
                            "s_rbi": "65",
                            "pos": "PH",
                            "id": "461235",
                            "rbi": "0",
                            "bo": "907",
                            "lob": "1",
                            "name": "Moss",
                            "slg": ".500",
                            "avg": ".232",
                            "bb": "0",
                            "fldg": ".000",
                            "note": "b-",
                            "ops": ".806",
                            "hbp": "0",
                            "d": "0",
                            "e": "0",
                            "so": "0",
                            "a": "0",
                            "s_so": "133",
                            "sf": "0",
                            "h": "0",
                            "cs": "0",
                            "obp": ".306",
                            "s_bb": "36",
                            "s_r": "61",
                            "t": "0",
                            "ao": "0",
                            "r": "0",
                            "sb": "0",
                            "po": "0",
                            "ab": "1",
                            "go": "2"
                        },
                        {
                            "hr": "0",
                            "sac": "0",
                            "name_display_first_last": "Jerome Williams",
                            "s_h": "0",
                            "s_hr": "0",
                            "s_rbi": "0",
                            "pos": "P",
                            "id": "425532",
                            "rbi": "0",
                            "bo": "908",
                            "lob": "0",
                            "name": "Williams, J",
                            "slg": ".000",
                            "avg": ".000",
                            "bb": "0",
                            "fldg": ".000",
                            "ops": ".000",
                            "hbp": "0",
                            "d": "0",
                            "e": "0",
                            "so": "0",
                            "a": "0",
                            "s_so": "1",
                            "sf": "0",
                            "h": "0",
                            "cs": "0",
                            "obp": ".000",
                            "s_bb": "0",
                            "s_r": "0",
                            "t": "0",
                            "ao": "0",
                            "r": "0",
                            "sb": "0",
                            "po": "0",
                            "ab": "0"
                        }
                    ],
                    "h": "5",
                    "text_data_es": "\n         <total_bases>Adams, M; Molina; Peralta, J; Wong; Garcia, G.</total_bases><br/>\n         <risp_lob_two_out>Carpenter.</risp_lob_two_out><br/>\n         <grounded_into_dp>Molina; Leake; Moss.</grounded_into_dp><br/>\n         <team_risp>\n            \t\t\t\t\t\t\tde 0-2.\n         </team_risp>\n         <team_lob>3.</team_lob>\n         <picked_off>Adams, M (1st base por Montero).</picked_off><br/><br/>",
                    "note_es": "\n         <pinch_hitters>a-Bateó por Socolovich en la 6th. b-Bateó por Duke en la 8th. </pinch_hitters>",
                    "text_data": "\n         <total_bases>Adams, M; Molina; Peralta, J; Wong; Garcia, G.</total_bases><br/>\n         <risp_lob_two_out>Carpenter.</risp_lob_two_out><br/>\n         <grounded_into_dp>Molina; Leake; Moss.</grounded_into_dp><br/>\n         <team_risp>0-for-2.</team_risp>\n         <team_lob>3.</team_lob>\n         <picked_off>Adams, M (1st base by Montero).</picked_off><br/><br/>",
                    "obp": ".324",
                    "rbi": "0",
                    "lob": "9",
                    "t": "0",
                    "r": "0",
                    "team_flag": "away",
                    "ab": "28",
                    "po": "24",
                    "slg": ".440",
                    "avg": ".254",
                    "bb": "2",
                    "note": "\n         <pinch_hitters>a-Singled for Socolovich in the 6th. b-Grounded into a double play for Duke in the 8th. </pinch_hitters>",
                    "ops": ".764"
                }
            ],
            "away_sname": "St. Louis",
            "game_id": "2016/09/23/slnmlb-chnmlb-1",
            "home_team_code": "chn",
            "venue_id": "17",
            "home_wins": "98",
            "away_team_code": "sln",
            "away_id": "138",
            "home_fname": "Chicago Cubs"
        }
    }
}